README.md
setup.py
whtools/__init__.py
whtools/morse.py
whtools/other.py
whtools.egg-info/PKG-INFO
whtools.egg-info/SOURCES.txt
whtools.egg-info/dependency_links.txt
whtools.egg-info/top_level.txt