Metadata-Version: 1.2
Name: whtools
Version: 0.0.7
Summary: My python tools all in one package
Home-page: https://github.com/WHGhost/whtools
Author: WHGhost
Author-email: wghosth@gmail.com
License: GPL-3.0
Keywords: library
Platform: UNKNOWN
Classifier: Development Status :: 3 - Alpha
Classifier: Topic :: Software Development :: Libraries
Classifier: License :: OSI Approved :: GNU General Public License (GPL)
Classifier: Programming Language :: Python :: 3
Requires-Python: >=3
